[
  {
    "patient_id": "P1001",
    "patient_name_given": "John",
    "patient_name_family": "Doe",
    "date_of_birth": "1985-07-14",
    "gender": "Male",
    "encounter_id": "E2001",
    "encounter_datetime": "2026-02-01T10:30:00Z",
    "encounter_location": "Ward A - Bed 1",
    "heart_rate_value": 78,
    "heart_rate_unit": "beats/min",
    "blood_pressure_systolic_value": 120,
    "blood_pressure_diastolic_value": 80,
    "respiratory_rate_value": 16,
    "temperature_value": 37.2,
    "oxygen_saturation_value": 98,
    "height_value": 175,
    "weight_value": 72,
    "bmi_value": 23.5,
    "clinical_notes": "Stable, no distress."
  },
  {
    "patient_id": "P1002",
    "patient_name_given": "Alice",
    "patient_name_family": "Smith",
    "date_of_birth": "1990-03-22",
    "gender": "Female",
    "encounter_id": "E2002",
    "encounter_datetime": "2026-02-01T11:00:00Z",
    "encounter_location": "Ward A - Bed 2",
    "heart_rate_value": 85,
    "heart_rate_unit": "beats/min",
    "blood_pressure_systolic_value": 118,
    "blood_pressure_diastolic_value": 76,
    "respiratory_rate_value": 18,
    "temperature_value": 36.8,
    "oxygen_saturation_value": 97,
    "height_value": 162,
    "weight_value": 60,
    "bmi_value": 22.8,
    "clinical_notes": "Mild cough, otherwise stable."
  },
  {
    "patient_id": "P1003",
    "patient_name_given": "Raj",
    "patient_name_family": "Kumar",
    "date_of_birth": "1975-11-05",
    "gender": "Male",
    "encounter_id": "E2003",
    "encounter_datetime": "2026-02-01T11:30:00Z",
    "encounter_location": "Ward B - Bed 3",
    "heart_rate_value": 92,
    "blood_pressure_systolic_value": 135,
    "blood_pressure_diastolic_value": 88,
    "respiratory_rate_value": 20,
    "temperature_value": 38.1,
    "oxygen_saturation_value": 95,
    "height_value": 170,
    "weight_value": 80,
    "bmi_value": 27.7,
    "clinical_notes": "Febrile, monitoring closely."
  },
  {
    "patient_id": "P1004",
    "patient_name_given": "Maria",
    "patient_name_family": "Lopez",
    "date_of_birth": "1982-01-15",
    "gender": "Female",
    "encounter_id": "E2004",
    "encounter_datetime": "2026-02-01T12:00:00Z",
    "encounter_location": "Ward B - Bed 4",
    "heart_rate_value": 70,
    "blood_pressure_systolic_value": 110,
    "blood_pressure_diastolic_value": 72,
    "respiratory_rate_value": 14,
    "temperature_value": 36.5,
    "oxygen_saturation_value": 99,
    "height_value": 168,
    "weight_value": 58,
    "bmi_value": 20.5,
    "clinical_notes": "Healthy, routine check."
  },
  {
    "patient_id": "P1005",
    "patient_name_given": "David",
    "patient_name_family": "Brown",
    "date_of_birth": "1968-09-09",
    "gender": "Male",
    "encounter_id": "E2005",
    "encounter_datetime": "2026-02-01T12:30:00Z",
    "encounter_location": "Ward C - Bed 5",
    "heart_rate_value": 88,
    "blood_pressure_systolic_value": 140,
    "blood_pressure_diastolic_value": 90,
    "respiratory_rate_value": 22,
    "temperature_value": 37.9,
    "oxygen_saturation_value": 94,
    "height_value": 180,
    "weight_value": 95,
    "bmi_value": 29.3,
    "clinical_notes": "Hypertensive, under observation."
  },
  {
    "patient_id": "P1006",
    "patient_name_given": "Sophia",
    "patient_name_family": "Williams",
    "date_of_birth": "2000-06-12",
    "gender": "Female",
    "encounter_id": "E2006",
    "encounter_datetime": "2026-02-01T13:00:00Z",
    "encounter_location": "Ward C - Bed 6",
    "heart_rate_value": 76,
    "blood_pressure_systolic_value": 115,
    "blood_pressure_diastolic_value": 75,
    "respiratory_rate_value": 15,
    "temperature_value": 36.9,
    "oxygen_saturation_value": 98,
    "height_value": 165,
    "weight_value": 55,
    "bmi_value": 20.2,
    "clinical_notes": "Routine exam, normal vitals."
  },
  {
    "patient_id": "P1007",
    "patient_name_given": "Chen",
    "patient_name_family": "Li",
    "date_of_birth": "1995-04-18",
    "gender": "Male",
    "encounter_id": "E2007",
    "encounter_datetime": "2026-02-01T13:30:00Z",
    "encounter_location": "Ward D - Bed 7",
    "heart_rate_value": 82,
    "blood_pressure_systolic_value": 125,
    "blood_pressure_diastolic_value": 82,
    "respiratory_rate_value": 17,
    "temperature_value": 37.0,
    "oxygen_saturation_value": 96,
    "height_value": 172,
    "weight_value": 68,
    "bmi_value": 23.0,
    "clinical_notes": "Mild fatigue reported."
  },
  {
    "patient_id": "P1008",
    "patient_name_given": "Fatima",
    "patient_name_family": "Ali",
    "date_of_birth": "1988-12-30",
    "gender": "Female",
    "encounter_id": "E2008",
    "encounter_datetime": "2026-02-01T14:00:00Z",
    "encounter_location": "Ward D - Bed 8",
    "heart_rate_value": 90,
    "blood_pressure_systolic_value": 130,
    "blood_pressure_diastolic_value": 85,
    "respiratory_rate_value": 19,
    "temperature_value": 37.4,
    "oxygen_saturation_value": 95,
    "height_value": 160,
    "weight_value": 70,
    "bmi_value": 27.3,
    "clinical_notes": "Overweight, advised lifestyle changes."
  },
  {
    "patient_id": "P1009",
    "patient_name_given": "Michael",
    "patient_name_family": "Johnson",
    "date_of_birth": "1972-08-25",
    "gender": "Male",
    "encounter_id": "E2009",
    "encounter_datetime": "2026-02-01T14:30:00Z",
    "encounter_location": "Ward E - Bed 9",
    "heart_rate_value": 95,
    "blood_pressure_systolic_value": 145,
    "blood_pressure_diastolic_value": 92,
    "respiratory_rate_value": 21,
    "temperature_value": 38.3,
    "oxygen_saturation_value": 93,
    "height_value": 178,
    "weight_value": 85,
    "bmi_value": 26.8,
    "clinical_notes": "Febrile, hypertensive."
  },
  {
    "patient_id": "P1010",
    "patient_name_given": "Emma",
    "patient_name_family": "Taylor",
    "date_of_birth": "1998-05-10",
    "gender": "Female",
    "encounter_id": "E2010",
    "encounter_datetime": "2026-02-01T15:00:00Z",
    "encounter_location": "Ward E - Bed 10",
    "heart_rate_value": 72,
    "blood_pressure_systolic_value": 112,
    "blood_pressure_diastolic_value": 70,
    "respiratory_rate_value": 15,
    "temperature_value": 36.6,
    "oxygen_saturation_value": 99,
    "height_value": 170,
    "weight_value": 62,
    "bmi_value": 21.5,  
    "clinical_notes": "Healthy, no complaints."
  } ]
